framepack/__init__.py
framepack/__main__.py
framepack/diffusers_helper/bucket_tools.py
framepack/diffusers_helper/clip_vision.py
framepack/diffusers_helper/dit_common.py
framepack/diffusers_helper/hf_login.py
framepack/diffusers_helper/hunyuan.py
framepack/diffusers_helper/memory.py
framepack/diffusers_helper/thread_utils.py
framepack/diffusers_helper/utils.py
framepack/diffusers_helper/gradio/progress_bar.py
framepack/diffusers_helper/k_diffusion/uni_pc_fm.py
framepack/diffusers_helper/k_diffusion/wrapper.py
framepack/diffusers_helper/models/hunyuan_video_packed.py
framepack/diffusers_helper/pipelines/k_diffusion_hunyuan.py
framepack-0.0.9.dist-info/LICENSE
framepack-0.0.9.dist-info/WHEEL
framepack-0.0.9.dist-info/METADATA
framepack-0.0.9.dist-info/RECORD
