Metadata-Version: 2.1
Name: framepack
Version: 0.0.9
Summary: 1-click video generator
Author-email: calcuis <info@calcu.io>
Classifier: License :: OSI Approved :: MIT License
Requires-Dist: tqdm
Requires-Dist: av
Project-URL: Download, https://github.com/calcuis/packpack/releases
Project-URL: GitHub, https://github.com/calcuis/packpack
Project-URL: Issues, https://github.com/calcuis/packpack/issues
